pigauth/__init__.py
pigauth/_auth.py
pigauth/_matcher.py
pigauth/_parser.py
pigauth/cli.py
pigauth/pigauth.py
pigauth-0.3.0.dist-info/LICENSE
pigauth-0.3.0.dist-info/METADATA
pigauth-0.3.0.dist-info/WHEEL
pigauth-0.3.0.dist-info/top_level.txt
pigauth-0.3.0.dist-info/RECORD
